tawnyapi/__init__.py
tawnyapi/vision/__init__.py
tawnyapi/vision/apitypes.py
tawnyapi/vision/cli.py
tawnyapi/vision/client.py
tawnyapi/vision/face_detector.py
tawnyapi/vision/util.py
tawnyapi-0.2.5.dist-info/METADATA
tawnyapi-0.2.5.dist-info/WHEEL
tawnyapi-0.2.5.dist-info/RECORD
